{
  "variants": {
    "facing=north,blockstate=0": {
      "model": "farout:block/electrolyzer"
    },
    "facing=east,blockstate=0": {
      "model": "farout:block/electrolyzer",
      "y": 90
    },
    "facing=south,blockstate=0": {
      "model": "farout:block/electrolyzer",
      "y": 180
    },
    "facing=west,blockstate=0": {
      "model": "farout:block/electrolyzer",
      "y": 270
    },
    "facing=north,blockstate=1": {
      "model": "farout:block/electrolyzer_blockstate_blockstate_0"
    },
    "facing=east,blockstate=1": {
      "model": "farout:block/electrolyzer_blockstate_blockstate_0",
      "y": 90
    },
    "facing=south,blockstate=1": {
      "model": "farout:block/electrolyzer_blockstate_blockstate_0",
      "y": 180
    },
    "facing=west,blockstate=1": {
      "model": "farout:block/electrolyzer_blockstate_blockstate_0",
      "y": 270
    }
  }
}