{
  "type": "minecraft:crafting_shaped",
  "category": "misc",
  "pattern": [
    "abc",
    "def",
    "geh"
  ],
  "key": {
    "a": {
      "item": "farout:display"
    },
    "b": {
      "item": "minecraft:glass"
    },
    "c": {
      "item": "farout:fan"
    },
    "d": {
      "item": "farout:medium_capacity_memory"
    },
    "e": {
      "item": "farout:aluminium_ingot"
    },
    "f": {
      "item": "farout:motor"
    },
    "g": {
      "item": "farout:medium_frequency_integrated_circuit"
    },
    "h": {
      "item": "farout:organic_molecules"
    }
  },
  "result": {
    "item": "farout:cryogenic_stasis_chamber",
    "count": 1
  }
}